sunshareservice/__init__.py
sunshareservice/cli.py
sunshareservice/sunshareservice_config.yaml
sunshareservice/service/__init__.py
sunshareservice/service/cons.py
sunshareservice/service/dbconnection.py
sunshareservice/service/main_router.py
sunshareservice/service/meteorological_router.py
sunshareservice/service/user_router.py
sunshareservice/service/wind_turbine_router.py
sunshareservice/util/__init__.py
sunshareservice/util/cons.py
sunshareservice/util/info_tool.py
sunshareservice/util/request_tool.py
sunshareservice/util/token_tool.py
sunshareservice/util/trafic_tool.py
shihua_sunshareservice-0.1.1.dist-info/LICENSE
shihua_sunshareservice-0.1.1.dist-info/METADATA
shihua_sunshareservice-0.1.1.dist-info/WHEEL
shihua_sunshareservice-0.1.1.dist-info/entry_points.txt
shihua_sunshareservice-0.1.1.dist-info/top_level.txt
shihua_sunshareservice-0.1.1.dist-info/RECORD
