Metadata-Version: 2.1
Name: shihua-sunshareservice
Version: 0.1.1
Summary: sunshareservice is a python sdk with data service.
Home-page: https://github.com/redblue0216/SunShareService
Author: shihua
Author-email: 15021408795@163.com
License: MIT
Requires-Python: >=3.10.9
License-File: LICENSE
